Espinosa/Pokem.csv
Espinosa/__init__.py
Espinosa/random_pokemon.py
Espinosa-3.0.6.dist-info/METADATA
Espinosa-3.0.6.dist-info/WHEEL
Espinosa-3.0.6.dist-info/top_level.txt
Espinosa-3.0.6.dist-info/RECORD
